docker_travis_php/__init__.py
docker_travis_php-0.2.1.data/scripts/docker-travis-php
docker_travis_php-0.2.1.dist-info/LICENSE.txt
docker_travis_php-0.2.1.dist-info/METADATA
docker_travis_php-0.2.1.dist-info/WHEEL
docker_travis_php-0.2.1.dist-info/top_level.txt
docker_travis_php-0.2.1.dist-info/zip-safe
docker_travis_php-0.2.1.dist-info/RECORD
