Metadata-Version: 2.1
Name: docker-travis-php
Version: 0.2.1
Summary: Shits out a simple dockerfile for php projects based upon a .travis.yml
Home-page: http://github.com/josegonzalez/docker-travis-php
Author: Jose Diaz-Gonzalez
Author-email: docker-travis-php@josediazgonzalez.com
License: The MIT License (MIT)
Requires-Dist: PyYAML (==3.13)
